LICENSE
MANIFEST.in
README.rst
setup.py
tempdirs.py
tempdirs.egg-info/PKG-INFO
tempdirs.egg-info/SOURCES.txt
tempdirs.egg-info/dependency_links.txt
tempdirs.egg-info/top_level.txt