Metadata-Version: 1.1
Name: tempdirs
Version: 0.0.7.1
Summary: tempdirs -- Safely create temporary directories
Home-page: https://github.com/thelinuxkid/tempdirs
Author: Andres Buritica
Author-email: andres@thelinuxkid.com
License: MIT
Platform: UNKNOWN
Classifier: Development Status :: 4 - Beta
Classifier: Intended Audience :: Developers
Classifier: Natural Language :: English
Classifier: License :: OSI Approved :: MIT License
Classifier: Programming Language :: Python
Classifier: Programming Language :: Python :: 2.7
